LICENSE
README.md
setup.cfg
setup.py
alis/__init__.py
alis/datasets/__init__.py
alis/feature_extraction/__init__.py
alis/feature_extraction/shingles.py
alis/feature_extraction/minhash/__init__.py
alis/feature_extraction/minhash/_base.py
alis/feature_extraction/minhash/hash_functions.py
alis/link_analysis/__init__.py
alis/link_analysis/_link_analysis.py
alis/link_analysis/test.py
alis/network_tools/__init__.py
alis/network_tools/clustering.py
alis/network_tools/metrics.py
alis/network_tools/plots.py
alis/similarity/__init__.py
alis/similarity/_jaccard.py
alis/similarity/minhash_lsh.py
alis/stream_mining/__init__.py
alis/stream_mining/_stream_mining.py
python_alis.egg-info/PKG-INFO
python_alis.egg-info/SOURCES.txt
python_alis.egg-info/dependency_links.txt
python_alis.egg-info/requires.txt
python_alis.egg-info/top_level.txt