Metadata-Version: 2.1
Name: python-alis
Version: 0.1.3
Summary: A collection of algorithms for scalable data science
Home-page: https://github.com/phdinds-aim/alis
Author: AIM PhDinDS 2024
Author-email: llorenzo@aim.edu
Maintainer: AIM PhDinDS 2024
Maintainer-email: llorenzo@aim.edu
License: UNKNOWN
Keywords: scalable,data science,networks,hash functions
Platform: UNKNOWN
License-File: LICENSE
